hemanth_hello_world/__init__.py
hemanth_hello_world/cli.py
hemanth_hello_world-0.10.dist-info/LICENSE
hemanth_hello_world-0.10.dist-info/METADATA
hemanth_hello_world-0.10.dist-info/WHEEL
hemanth_hello_world-0.10.dist-info/entry_points.txt
hemanth_hello_world-0.10.dist-info/top_level.txt
hemanth_hello_world-0.10.dist-info/RECORD
