Metadata-Version: 2.1
Name: hemanth_hello_world
Version: 0.10
Summary: A simple package to multiply two numbers
Author: Hemanthbollina123
Author-email: hsbollina@example.com
Classifier: Programming Language :: Python :: 3
Classifier: License :: OSI Approved :: MIT License
Classifier: Operating System :: OS Independent
License-File: LICENSE
